setup.py
sydbank_exporter/__init__.py
sydbank_exporter.egg-info/PKG-INFO
sydbank_exporter.egg-info/SOURCES.txt
sydbank_exporter.egg-info/dependency_links.txt
sydbank_exporter.egg-info/requires.txt
sydbank_exporter.egg-info/top_level.txt