Metadata-Version: 1.0
Name: sydbank-exporter
Version: 0.1.0
Summary: Create a CSV file that can be read by Sydbank
Home-page: https://github.com/joshuakarjala/sydbank-exporter
Author: Joshua Karjala-Svendsen
Author-email: joshua@founders.as
License: UNKNOWN
Platform: UNKNOWN
